zuperscripts/TransactionERC.py
zuperscripts/TransactionNEAR.py
zuperscripts/__init__.py
zuperscripts/main.py
zuperscripts-0.0.1.dist-info/LICENSE
zuperscripts-0.0.1.dist-info/METADATA
zuperscripts-0.0.1.dist-info/WHEEL
zuperscripts-0.0.1.dist-info/top_level.txt
zuperscripts-0.0.1.dist-info/RECORD
