Metadata-Version: 2.1
Name: zuperscripts
Version: 0.0.1
Summary: Collection of web3 scripts
Home-page: https://github.com/nmluthfi/web3-scripts.git
Author: Zuperhunt
Author-email: nurmuhammadluthfi@gmail.com
License: MIT
Project-URL: Source, https://github.com/nmluthfi/web3-scripts.git
Keywords: python,transaction,web3,scripts
License-File: LICENSE
Requires-Dist: requests
